pynumerals/__init__.py
pynumerals/errorcheck.py
pynumerals/glottocode_matcher.py
pynumerals/mappings.py
pynumerals/number_parser.py
pynumerals/numerals_html.py
pynumerals/numerals_utils.py
pynumerals/process_html.py
pynumerals/value_parser.py
pynumerals/commands/__init__.py
pynumerals/commands/create_language_sheet.py
pynumerals-1.0.1.dist-info/LICENSE
pynumerals-1.0.1.dist-info/METADATA
pynumerals-1.0.1.dist-info/WHEEL
pynumerals-1.0.1.dist-info/entry_points.txt
pynumerals-1.0.1.dist-info/top_level.txt
pynumerals-1.0.1.dist-info/RECORD
