Metadata-Version: 2.1
Name: pynumerals
Version: 1.0.1
Summary: Helper library for numeralbank projects
Home-page: https://github.com/numeralbank/pynumerals
Author: Hans-Jörg Bibiko, Christoph Rzymski, Robert Forkel
Author-email: lingweb@shh.mpg.de
License: Apache 2.0
Project-URL: Bug Tracker, https://github.com/numeralbank/pynumerals/issues
Keywords: data
Platform: UNKNOWN
Classifier: Programming Language :: Python
Classifier: Programming Language :: Python :: 3
Classifier: Programming Language :: Python :: 3.6
Classifier: Programming Language :: Python :: 3.7
Classifier: Programming Language :: Python :: 3.8
Classifier: Programming Language :: Python :: 3.9
Classifier: Programming Language :: Python :: 3.10
Classifier: License :: OSI Approved :: Apache Software License
Requires-Python: >=3.5
License-File: LICENSE
Requires-Dist: attr
Requires-Dist: beautifulsoup4 (>=4.9.1)
Requires-Dist: clldutils (>=3.5.4)
Requires-Dist: pylexibank (>=2.8.2)
Requires-Dist: openpyxl (>=3.0.5)
Requires-Dist: python-levenshtein (>=0.12)
Requires-Dist: fuzzywuzzy (>=0.18)
Provides-Extra: dev
Requires-Dist: flake8 ; extra == 'dev'
Requires-Dist: build ; extra == 'dev'
Requires-Dist: twine ; extra == 'dev'
Requires-Dist: tox ; extra == 'dev'
Provides-Extra: test
Requires-Dist: pytest (>=6.0.2) ; extra == 'test'
Requires-Dist: pytest-mock (>=3.3.1) ; extra == 'test'
Requires-Dist: pytest-cov (>=2.10.1) ; extra == 'test'
Requires-Dist: coverage (>=5.3) ; extra == 'test'
Requires-Dist: pyglottolog (>=3.2.2) ; extra == 'test'
